LICENSE
MANIFEST.in
README.md
pyproject.toml
setup.py
pyearthriver/__init__ copy.py
pyearthriver/__init__.py
pyearthriver.egg-info/PKG-INFO
pyearthriver.egg-info/SOURCES.txt
pyearthriver.egg-info/dependency_links.txt
pyearthriver.egg-info/requires.txt
pyearthriver.egg-info/top_level.txt
pyearthriver/algorithms/__init__.py
pyearthriver/algorithms/auxiliary/find_index_in_list.py
pyearthriver/algorithms/auxiliary/find_vertex_in_list.py
pyearthriver/algorithms/cython/kernel.cpp
pyearthriver/algorithms/cython/kernel.pyx
pyearthriver/classes/__init__.py
pyearthriver/classes/confluence.py
pyearthriver/classes/edge.py
pyearthriver/classes/flowline.py
pyearthriver/classes/rivergraph.py
pyearthriver/classes/vertex.py
pyearthriver/formats/__init__.py
pyearthriver/formats/export_flowline.py
pyearthriver/formats/export_vertex.py
pyearthriver/formats/find_index_in_list.py
pyearthriver/formats/find_vertex_in_list.py