Metadata-Version: 2.4
Name: pyearthriver
Version: 0.1.0
Summary: A Python library for analyzing and processing river network flowlines using graph-based algorithms
Author-email: Chang Liao <changliao.climate@gmail.com>
License: BSD-3-Clause
Project-URL: Homepage, https://github.com/changliao1025/pyearthriver
Project-URL: Documentation, https://github.com/changliao1025/pyearthriver
Project-URL: Repository, https://github.com/changliao1025/pyearthriver
Project-URL: Bug Tracker, https://github.com/changliao1025/pyearthriver/issues
Keywords: river,network,graph,hydrology,flowlines,stream network
Classifier: Development Status :: 4 - Beta
Classifier: Intended Audience :: Science/Research
Classifier: License :: OSI Approved :: BSD License
Classifier: Operating System :: OS Independent
Classifier: Programming Language :: Python :: 3
Classifier: Programming Language :: Python :: 3.8
Classifier: Programming Language :: Python :: 3.9
Classifier: Programming Language :: Python :: 3.10
Classifier: Programming Language :: Python :: 3.11
Classifier: Programming Language :: Python :: 3.12
Classifier: Topic :: Scientific/Engineering :: GIS
Classifier: Topic :: Scientific/Engineering :: Hydrology
Requires-Python: >=3.8
License-File: LICENSE
Requires-Dist: numpy>=1.20.0
Requires-Dist: scipy>=1.7.0
Requires-Dist: pyearth>=0.2.0
Requires-Dist: rtree>=0.9.0
Provides-Extra: dev
Requires-Dist: pytest>=7.0; extra == "dev"
Requires-Dist: pytest-cov>=4.0; extra == "dev"
Requires-Dist: black>=23.0; extra == "dev"
Requires-Dist: flake8>=6.0; extra == "dev"
Dynamic: license-file
